{"IcoMoonType":"selection","icons":[{"icon":{"paths":["M170.24 435.2q-51.2 0-87.253-36.053t-36.053-87.040 36.053-87.040 87.040-36.053 87.253 36.053 36.267 87.253q0 33.28-16.64 61.653t-45.013 44.8-61.653 16.427zM510.72 435.2q-51.2 0-87.253-36.053t-36.053-86.827q0-25.173 9.813-48t26.24-39.253 39.253-26.24 48-9.813q50.773 0 86.827 36.053t36.053 87.253q0 19.627-6.187 38.613t-17.493 33.92-26.453 26.453-33.92 17.707-38.827 6.187zM851.2 435.2q-51.2 0-87.253-36.053t-36.053-86.827q0-33.707 16.64-62.080t44.8-44.8 61.867-16.427q24.747 0 47.573 9.813t39.467 26.24 26.24 39.253 9.6 47.787-9.6 47.787-26.24 39.253-39.467 26.24-47.573 9.813z"],"isMulticolor":false,"isMulticolor2":false,"defaultCode":57736,"grid":0,"attrs":[]},"attrs":[],"properties":{"id":188,"order":202,"ligatures":"","prevSize":32,"code":57736,"name":"uniE188"},"setIdx":1,"setId":0,"iconIdx":187},{"icon":{"paths":["M415.147 754.773l-156.587-156.587 290.987-290.987-290.987-290.987 156.587-156.587 448 447.573z"],"isMulticolor":false,"isMulticolor2":false,"defaultCode":57892,"grid":0,"attrs":[]},"attrs":[],"properties":{"id":224,"order":203,"ligatures":"","prevSize":32,"code":57892,"name":"uniE224"},"setIdx":1,"setId":0,"iconIdx":223},{"icon":{"paths":["M610.133 754.773l-447.573-447.573 447.573-447.573 156.587 156.587-290.56 290.987 290.987 290.987z"],"isMulticolor":false,"isMulticolor2":false,"defaultCode":57893,"grid":0,"attrs":[]},"attrs":[],"properties":{"id":225,"order":204,"ligatures":"","prevSize":32,"code":57893,"name":"uniE225"},"setIdx":1,"setId":0,"iconIdx":224},{"icon":{"paths":["M802.987 605.867l-290.987-290.987-290.987 290.987-156.587-157.013 447.573-447.573 447.573 447.573z"],"isMulticolor":false,"isMulticolor2":false,"defaultCode":58881,"grid":0,"attrs":[]},"attrs":[],"properties":{"id":601,"order":205,"ligatures":"","prevSize":32,"code":58881,"name":"uniE601"},"setIdx":1,"setId":0,"iconIdx":600},{"icon":{"paths":["M512 613.12l-447.573-447.573 156.587-157.013 290.987 290.987 290.987-290.987 156.587 157.013z"],"isMulticolor":false,"isMulticolor2":false,"defaultCode":58882,"grid":0,"attrs":[]},"attrs":[],"properties":{"id":602,"order":206,"ligatures":"","prevSize":32,"code":58882,"name":"uniE602"},"setIdx":1,"setId":0,"iconIdx":601}],"height":1024,"metadata":{"name":"icomoon"},"preferences":{"showGlyphs":true,"showQuickUse":true,"showQuickUse2":true,"showSVGs":true,"fontPref":{"prefix":"icon-","metadata":{"fontFamily":"icomoon"},"metrics":{"emSize":1024,"baseline":20,"whitespace":null},"embed":false},"imagePref":{"prefix":"icon-","png":true,"useClassSelector":true,"color":0,"bgColor":16777215,"classSelector":".icon","name":"icomoon"},"historySize":50,"showCodes":true,"gridSize":16}}